transfer_sh_client/__init__.py
transfer_sh_client/manager.py
python_transfer_sh-0.0.1.dist-info/METADATA
python_transfer_sh-0.0.1.dist-info/WHEEL
python_transfer_sh-0.0.1.dist-info/RECORD
