Metadata-Version: 2.4
Name: python-transfer-sh
Version: 0.0.1
Summary: A python client for transfer.sh
Project-URL: Homepage, https://github.com/daswer123/transfersh-client
Project-URL: Bug Tracker, https://github.com/daswer123/transfersh-client/issues
Author-email: daswer123 <daswerq123@gmail.com>
Classifier: License :: OSI Approved :: MIT License
Classifier: Operating System :: OS Independent
Classifier: Programming Language :: Python :: 3
Requires-Python: >=3.9
Requires-Dist: requests
